CMakeLists.txt
MANIFEST.in
README.md
pyproject.toml
setup.py
pp_sketch/__init__.py
pp_sketch/__main__.py
pp_sketch/matrix.py
pp_sketchlib.egg-info/PKG-INFO
pp_sketchlib.egg-info/SOURCES.txt
pp_sketchlib.egg-info/dependency_links.txt
pp_sketchlib.egg-info/entry_points.txt
pp_sketchlib.egg-info/not-zip-safe
pp_sketchlib.egg-info/requires.txt
pp_sketchlib.egg-info/top_level.txt
src/Makefile
src/api.cpp
src/api.hpp
src/json.hpp
src/reference.cpp
src/reference.hpp
src/robin_hood.h
src/sketchlib_bindings.cpp
src/version.h
src/database/database.cpp
src/database/database.hpp
src/database/hdf5_funcs.hpp
src/dist/dist.cpp
src/dist/dist.hpp
src/dist/linear_regression.cpp
src/dist/matrix.hpp
src/dist/matrix_idx.hpp
src/dist/matrix_ops.cpp
src/dist/matrix_types.hpp
src/gpu/align.hpp
src/gpu/containers.cuh
src/gpu/cuda.cuh
src/gpu/device_memory.cu
src/gpu/device_memory.cuh
src/gpu/device_reads.cu
src/gpu/device_reads.cuh
src/gpu/dist.cu
src/gpu/gpu.hpp
src/gpu/gpu_api.cpp
src/gpu/gpu_countmin.cu
src/gpu/gpu_countmin.cuh
src/gpu/sketch.cu
src/random/random_match.cpp
src/random/random_match.hpp
src/random/rng.cpp
src/random/rng.hpp
src/random/kmeans/KMeansRexCore.cpp
src/random/kmeans/KMeansRexCore.h
src/random/kmeans/KMeansRexCoreInterface.h
src/random/kmeans/mersenneTwister2002.c
src/sketch/bitfuncs.hpp
src/sketch/countmin.cpp
src/sketch/countmin.hpp
src/sketch/kseq.h
src/sketch/ntHashIterator.hpp
src/sketch/nthash.hpp
src/sketch/nthash_tables.hpp
src/sketch/progress.hpp
src/sketch/seqio.cpp
src/sketch/seqio.hpp
src/sketch/sketch.cpp
src/sketch/sketch.hpp
src/sketch/stHashIterator.hpp
src/web/.gitignore
src/web/web_sketch.cpp
test/test-dists.py
test/test-matrix.py
vendor/highfive/.clang-format
vendor/highfive/.gitignore
vendor/highfive/.gitmodules
vendor/highfive/.travis.yml
vendor/highfive/CHANGELOG.md
vendor/highfive/CMakeLists.txt
vendor/highfive/LICENSE
vendor/highfive/README.md
vendor/highfive/VERSION
vendor/highfive/default.nix
vendor/highfive/.github/build.sh
vendor/highfive/.github/pull_request_template.md
vendor/highfive/.github/ISSUE_TEMPLATE/bug_report.md
vendor/highfive/.github/ISSUE_TEMPLATE/feature_request.md
vendor/highfive/.github/workflows/ci.yml
vendor/highfive/.github/workflows/gh-pages.yml
