Metadata-Version: 2.1
Name: pp-sketchlib
Version: 2.1.1
Summary: Library of sketching functions used by PopPUNK
Home-page: https://github.com/johnlees/pp-sketchlib
Author: John Lees
Author-email: john@johnlees.me
License: Apache Software License
Keywords: bacteria genomics population-genetics k-mer
Platform: UNKNOWN
Classifier: Development Status :: 4 - Beta
Classifier: Intended Audience :: Science/Research
Classifier: Topic :: Scientific/Engineering :: Bio-Informatics
Classifier: License :: OSI Approved :: Apache Software License
Classifier: Programming Language :: Python :: 3.8
Requires-Python: >=3.8.0
